audiochunker/__init__.py
audiochunker-0.2.1.dist-info/LICENSE
audiochunker-0.2.1.dist-info/METADATA
audiochunker-0.2.1.dist-info/WHEEL
audiochunker-0.2.1.dist-info/top_level.txt
audiochunker-0.2.1.dist-info/RECORD
